mypackage/__init__.py
mypackage/module1.py
tests/__init__.py
Ragzhongshui-0.1.0.dist-info/LICENSE
Ragzhongshui-0.1.0.dist-info/METADATA
Ragzhongshui-0.1.0.dist-info/WHEEL
Ragzhongshui-0.1.0.dist-info/top_level.txt
Ragzhongshui-0.1.0.dist-info/RECORD
