Metadata-Version: 2.1
Name: Ragzhongshui
Version: 0.1.0
Summary: A simple example Python package
Home-page: https://github.com/yourusername/mypackage
Author: Your Name
Author-email: your.email@example.com
Classifier: Programming Language :: Python :: 3
Classifier: License :: OSI Approved :: MIT License
Classifier: Operating System :: OS Independent
Requires-Python: >=3.10
License-File: LICENSE
Requires-Dist: requests
Requires-Dist: pandas
Requires-Dist: openai
Requires-Dist: ragchecker
Requires-Dist: spacy
